{"@context":"https://iiif.io/api/presentation/3/context.json","id":"https://potential-adventure-6391vr6.pages.github.io/api/facet/subject/fqh-abadat.json","type":"Collection","label":{"none":["فقه: عبادات"]},"items":[{"id":"https://iiif-maktaba.dc.library.northwestern.edu/f0779514-e7c3-41b9-89d0-38ceea3f0e8a.json","type":"Manifest","label":{"none":["Poem on the Use of the Siwāk (tooth stick)"]},"thumbnail":[{"id":"https://api.dc.library.northwestern.edu/api/v2/works/d7f5cb30-54c7-4070-9111-0c5876d79ee2/thumbnail","type":"Image","format":"image/jpeg","height":300,"width":300}],"homepage":[{"id":"https://potential-adventure-6391vr6.pages.github.io/works/poem-on-the-use-of-the-siwak-tooth-stick","type":"Text","label":{"none":["Poem on the Use of the Siwāk (tooth stick)"]}}]}],"partOf":[{"id":"https://potential-adventure-6391vr6.pages.github.io/api/facet/subject.json","type":"Collection"}],"summary":{"none":["Subject"]},"homepage":[{"id":"https://potential-adventure-6391vr6.pages.github.io/search?subject=fqh-abadat","type":"Text","label":{"none":["فقه: عبادات"]}}]}