{"@context":"https://iiif.io/api/presentation/3/context.json","id":"https://nulib-ds.github.io/maktaba/api/facet/date/650-to-2010.json","type":"Collection","label":{"none":["650? to 2010?"]},"items":[{"id":"https://iiif-maktaba.dc.library.northwestern.edu/9d824aee-421f-4f69-b6d6-65ac6b9cbb02.json","type":"Manifest","label":{"none":["A Treatise and Good Advice to the Accountable People of this Time (Qadi Modibbo Abdullahi b. Muḥammad Bellel, d. 1903)"]},"thumbnail":[{"id":"https://api.dc.library.northwestern.edu/api/v2/works/21e0766f-9d7b-41b6-9ce8-40a99f600976/thumbnail","type":"Image","format":"image/jpeg","height":300,"width":300}],"homepage":[{"id":"https://nulib-ds.github.io/maktaba/works/a-treatise-and-good-advice-to-the-accountable-people-of-this-time-qadi-modibbo-abdullahi-b-muammad-b","type":"Text","label":{"none":["A Treatise and Good Advice to the Accountable People of this Time (Qadi Modibbo Abdullahi b. Muḥammad Bellel, d. 1903)"]}}]},{"id":"https://iiif-maktaba.dc.library.northwestern.edu/31404bbc-93da-43a5-9020-de63e3b40a9b.json","type":"Manifest","label":{"none":["Weeping Has Become Warranted (Aḥmadu Bamba Mbacke, d. 1927)"]},"thumbnail":[{"id":"https://api.dc.library.northwestern.edu/api/v2/works/4f4f57fd-8c59-4bc4-9598-d2c9746a3465/thumbnail","type":"Image","format":"image/jpeg","height":300,"width":300}],"homepage":[{"id":"https://nulib-ds.github.io/maktaba/works/weeping-has-become-warranted-amadu-bamba-mbacke-d-1927","type":"Text","label":{"none":["Weeping Has Become Warranted (Aḥmadu Bamba Mbacke, d. 1927)"]}}]}],"partOf":[{"id":"https://nulib-ds.github.io/maktaba/api/facet/date.json","type":"Collection"}],"summary":{"none":["Date"]},"homepage":[{"id":"https://nulib-ds.github.io/maktaba/search?date=650-to-2010","type":"Text","label":{"none":["650? to 2010?"]}}]}